{"telescope-fzf-native.nvim": {"commit": "6791f74"}, "packer.nvim": {"commit": "afab8959"}, "vim-enmasse": {"commit": "c2286f1"}, "vim-surround": {"commit": "bf3480d"}, "nvim-lspconfig": {"commit": "da7461b"}, "vim-dispatch": {"commit": "00e77d9"}, "vim-sayonara": {"commit": "75c73f3"}, "nvim-lightbulb": {"commit": "1e2844b"}, "vim-fugitive": {"commit": "66a921b"}, "splitjoin.vim": {"commit": "ab9d5cd"}, "null-ls.nvim": {"commit": "8c90ccf"}, "telescope-ui-select.nvim": {"commit": "62ea5e5"}, "which-key.nvim": {"commit": "bd4411a"}, "telescope-file-browser.nvim": {"commit": "4272c52"}, "nvim-treesitter-textobjects": {"commit": "a264d5a"}, "cmp-nvim-lsp": {"commit": "affe808"}, "cmp_luasnip": {"commit": "a9de941"}, "nvim-lsp-ts-utils": {"commit": "0a6a16e"}, "rust-tools.nvim": {"commit": "af266e4"}, "neogit": {"commit": "05386ff"}, "gitsigns.nvim": {"commit": "29468d8"}, "indent-blankline.nvim": {"commit": "c15bbe9"}, "nvim-ts-autotag": {"commit": "fdefe46"}, "lightspeed.nvim": {"commit": "977ca1a"}, "telescope.nvim": {"commit": "d793de0"}, "trouble.nvim": {"commit": "da61737"}, "nvim-ts-context-commentstring": {"commit": "4befb89"}, "vim-dirvish": {"commit": "81b4087"}, "Comment.nvim": {"commit": "4818a4c"}, "vim-unimpaired": {"commit": "efdc647"}, "todo-comments.nvim": {"commit": "98b1ebf"}, "nvim-autopairs": {"commit": "34bd374"}, "playground": {"commit": "ce7e4b7"}, "LuaSnip": {"commit": "b8fa22f"}, "diffview.nvim": {"commit": "a45163c"}, "vim-matchup": {"commit": "3cebd21"}, "nvim-web-devicons": {"commit": "2d02a56"}, "vim-repeat": {"commit": "24afe92"}, "nvim-treesitter": {"commit": "48d88dd"}, "nvim-jdtls": {"commit": "87bdf2b"}, "modus-theme-vim": {"commit": "841a8c3"}, "vim-eunuch": {"commit": "74e0e16"}, "toggleterm.nvim": {"commit": "1a8b330"}, "plenary.nvim": {"commit": "31807ee"}, "nvim-cmp": {"commit": "706371f"}, "nvim-treesitter-context": {"commit": "8e88b67"}, "cmp-path": {"commit": "447c87c"}, "lightline.vim": {"commit": "b02ef0d"}, "cmp-buffer": {"commit": "3022dbc"}, "cmp-nvim-lua": {"commit": "d276254"}, "vim-polyglot": {"commit": "38282d58"}}
